synapticonn/__init__.py
synapticonn/version.py
synapticonn/core/__init__.py
synapticonn/core/connections.py
synapticonn/core/core_utils.py
synapticonn/core/info.py
synapticonn/core/spike_times.py
synapticonn/features/__init__.py
synapticonn/features/ccg_stability.py
synapticonn/features/mono_connection_latency.py
synapticonn/features/mono_connection_peak.py
synapticonn/monosynaptic_connections/__init__.py
synapticonn/monosynaptic_connections/ccg_connection_type.py
synapticonn/monosynaptic_connections/ccg_synaptic_strength.py
synapticonn/plots/__init__.py
synapticonn/plots/acg.py
synapticonn/plots/aesthetics.py
synapticonn/plots/ccg.py
synapticonn/plots/plot_utils.py
synapticonn/plots/save.py
synapticonn/plots/settings.mplstyle
synapticonn/plots/spiketrain.py
synapticonn/plots/style.py
synapticonn/plots/synaptic_strength_calc.py
synapticonn/postprocessing/__init__.py
synapticonn/postprocessing/autocorrelograms.py
synapticonn/postprocessing/correlogram_utils.py
synapticonn/postprocessing/crosscorrelograms.py
synapticonn/quality_metrics/__init__.py
synapticonn/quality_metrics/isi_violations.py
synapticonn/quality_metrics/presence_ratio.py
synapticonn/quality_metrics/unit_fr.py
synapticonn/utils/__init__.py
synapticonn/utils/attribute_checks.py
synapticonn/utils/data_utils.py
synapticonn/utils/errors.py
synapticonn/utils/file_io.py
synapticonn/utils/mod_utils.py
synapticonn/utils/report.py
synapticonn/utils/warnings.py
tests/__init__.py
tests/test_fit.py
tests/test_initialization.py
tests/tutils.py
synapticonn-0.0.1rc4.dist-info/LICENSE
synapticonn-0.0.1rc4.dist-info/METADATA
synapticonn-0.0.1rc4.dist-info/WHEEL
synapticonn-0.0.1rc4.dist-info/top_level.txt
synapticonn-0.0.1rc4.dist-info/RECORD
