Metadata-Version: 2.1
Name: synapticonn
Version: 0.0.1rc4
Summary: Inferring monosynaptic connections in neural circuits.
Home-page: https://github.com/mzabolocki/SynaptiConn
Author: Michael Zabolocki
Author-email: mzabolocki@gmail.com
Maintainer-email: mzabolocki@gmail.com
License: Apache License, 2.0
Keywords: neuroscience,connectomics,synaptic connections
Platform: any
Classifier: Development Status :: 5 - Production/Stable
Classifier: Intended Audience :: Science/Research
Classifier: Topic :: Scientific/Engineering
Classifier: License :: OSI Approved :: Apache Software License
Classifier: Operating System :: Microsoft :: Windows
Classifier: Operating System :: MacOS
Classifier: Operating System :: POSIX
Classifier: Operating System :: Unix
Classifier: Programming Language :: Python
Classifier: Programming Language :: Python :: 3.8
Classifier: Programming Language :: Python :: 3.9
Classifier: Programming Language :: Python :: 3.10
Classifier: Programming Language :: Python :: 3.11
Requires-Python: >=3.8
License-File: LICENSE
Requires-Dist: jupyter
Requires-Dist: ipykernel
Requires-Dist: numpy
Requires-Dist: scipy
Requires-Dist: pandas
Requires-Dist: matplotlib
Requires-Dist: ipympl
Requires-Dist: openpyxl
Requires-Dist: joblib
